<?xml version="1.0" encoding="UTF-8"?>
<!DOCTYPE mapper PUBLIC "-//mybatis.org//DTD Mapper 3.0//EN" "http://mybatis.org/dtd/mybatis-3-mapper.dtd">
<mapper namespace="com.windthunder.machineroom.monitoring.mapper.CollectorMapper">
  <resultMap id="BaseResultMap" type="com.windthunder.machineroom.monitoring.domain.Collector">
    <!--@mbg.generated generated on Wed May 20 17:32:13 CST 2020.-->
    <!--@Table collector-->
    <id column="id" jdbcType="CHAR" property="id" />
    <result column="name" jdbcType="CHAR" property="name" />
    <result column="pid" jdbcType="CHAR" property="pid" />
    <result column="model" jdbcType="BLOB" property="model" />
  </resultMap>
  <sql id="Base_Column_List">
    <!--@mbg.generated generated on Wed May 20 17:32:13 CST 2020.-->
    id, `name`, pid, model
  </sql>

<!--auto generated by MybatisCodeHelper on 2020-05-21-->
  <select id="findByAll" resultMap="BaseResultMap">
        select
        <include refid="Base_Column_List"/>
        from collector
        <where>
            <if test="id != null">
                and id=#{id,jdbcType=CHAR}
            </if>
            <if test="name != null">
                and `name`=#{name,jdbcType=CHAR}
            </if>
            <if test="pid != null">
                and pid=#{pid,jdbcType=CHAR}
            </if>
            <if test="model != null">
                and model=#{model,jdbcType=BLOB}
            </if>
        </where>
    </select>
</mapper>